COPYING.AGPL-3
COPYING.LGPL-3
HACKING
INSTALL
MANIFEST.in
NEWS
README
setup-dev-env.sh
setup.py
dashboard_app/__init__.py
dashboard_app/admin.py
dashboard_app/context_processors.py
dashboard_app/dispatcher.py
dashboard_app/helpers.py
dashboard_app/managers.py
dashboard_app/models.py
dashboard_app/urls.py
dashboard_app/views.py
dashboard_app/xmlrpc.py
dashboard_app/data_sources/__init__.py
dashboard_app/data_sources/gcc.py
dashboard_app/fixtures/hacking_admin_user.json
dashboard_app/fixtures/hacking_gcc_bundle_stream.json
dashboard_app/fixtures/hacking_initial_bundle_stream.json
dashboard_app/fixtures/hacking_localhost_site.json
dashboard_app/fixtures/test_run_detail.json
dashboard_app/reports/__init__.py
dashboard_app/reports/gcc.py
dashboard_app/templates/403.html
dashboard_app/templates/404.html
dashboard_app/templates/dashboard_app/api.html
dashboard_app/templates/dashboard_app/attachment_detail.html
dashboard_app/templates/dashboard_app/bundle_stream_list.html
dashboard_app/templates/dashboard_app/test_result_detail.html
dashboard_app/templates/dashboard_app/test_run_detail.html
dashboard_app/templates/dashboard_app/test_run_hardware_context.html
dashboard_app/templates/dashboard_app/test_run_list.html
dashboard_app/templates/dashboard_app/test_run_software_context.html
dashboard_app/tests/__init__.py
dashboard_app/tests/fixtures.py
dashboard_app/tests/urls.py
dashboard_app/tests/utils.py
dashboard_app/tests/models/__init__.py
dashboard_app/tests/models/attachment.py
dashboard_app/tests/models/bundle.py
dashboard_app/tests/models/bundle_deserialization_error.py
dashboard_app/tests/models/bundle_stream.py
dashboard_app/tests/models/hw_device.py
dashboard_app/tests/models/named_attribute.py
dashboard_app/tests/models/sw_package.py
dashboard_app/tests/models/test.py
dashboard_app/tests/models/test_case.py
dashboard_app/tests/models/test_result.py
dashboard_app/tests/models/test_run.py
dashboard_app/tests/other/__init__.py
dashboard_app/tests/other/csrf.py
launch_control.egg-info/PKG-INFO
launch_control.egg-info/SOURCES.txt
launch_control.egg-info/dependency_links.txt
launch_control.egg-info/not-zip-safe
launch_control.egg-info/requires.txt
launch_control.egg-info/top_level.txt
