Metadata-Version: 1.0
Name: launch-control
Version: 0.3
Summary: Dashboard for linaro LAVA stack
Home-page: https://launchpad.net/launch-control
Author: Zygmunt Krynicki
Author-email: zygmunt.krynicki@linaro.org
License: AGPL
Platform: UNKNOWN
Classifier: Development Status :: 3 - Alpha
Classifier: Intended Audience :: Developers
Classifier: License :: OSI Approved :: GNU Affero General Public License v3
Classifier: License :: OSI Approved :: GNU Library or Lesser General Public License (LGPL)
Classifier: Operating System :: OS Independent
Classifier: Programming Language :: Python :: 2.6
Classifier: Topic :: Software Development :: Testing
